pygreat/__init__.py
pygreat/board.py
pygreat/comms.py
pygreat/errors.py
pygreat/classes/__init__.py
pygreat/classes/core.py
pygreat/comms_backends/__init__.py
pygreat/comms_backends/usb.py
pygreat/comms_backends/usb1.py
pygreat-2024.0.5.dist-info/METADATA
pygreat-2024.0.5.dist-info/WHEEL
pygreat-2024.0.5.dist-info/top_level.txt
pygreat-2024.0.5.dist-info/RECORD
