Metadata-Version: 2.4
Name: pygreat
Version: 2024.0.5
Summary: Python library for talking with libGreat devices
Author-email: Great Scott Gadgets <dev@greatscottgadgets.com>
License: BSD
Project-URL: Documentation, https://greatfet.readthedocs.io
Project-URL: Repository, https://github.com/greatscottgadgets/libgreat
Project-URL: Issues, https://github.com/greatscottgadgets/libgreat/issues
Classifier: Development Status :: 5 - Production/Stable
Classifier: Programming Language :: Python :: 3
Classifier: License :: OSI Approved :: BSD License
Classifier: Operating System :: OS Independent
Classifier: Natural Language :: English
Classifier: Environment :: Console
Classifier: Environment :: Plugins
Classifier: Intended Audience :: Developers
Classifier: Intended Audience :: Science/Research
Classifier: Topic :: Scientific/Engineering
Classifier: Topic :: Security
Requires-Python: >=3.9
Requires-Dist: pyusb
Requires-Dist: backports.functools_lru_cache
